pyesmda/__init__.py
pyesmda/esmda.py
pyesmda-0.2.0.dist-info/AUTHORS.rst
pyesmda-0.2.0.dist-info/LICENSE
pyesmda-0.2.0.dist-info/METADATA
pyesmda-0.2.0.dist-info/WHEEL
pyesmda-0.2.0.dist-info/top_level.txt
pyesmda-0.2.0.dist-info/RECORD
