Metadata-Version: 2.1
Name: pyesmda
Version: 0.2.0
Summary: Python Ensemble Smoother with Multiple Data Assimilations
Home-page: https://gitlab.com/antoinecollet5/pyesmda
Author: Antoine Collet
Author-email: antoine.collet5@gmail.com
License: MIT license
Keywords: esmda,es-mda,inversion,inverse problem,parameter estimation,stochastic-optimization,ensemble smoother
Platform: UNKNOWN
Classifier: Development Status :: 2 - Pre-Alpha
Classifier: Intended Audience :: Developers
Classifier: License :: OSI Approved :: MIT License
Classifier: Natural Language :: English
Classifier: Programming Language :: Python :: 3
Classifier: Programming Language :: Python :: 3.6
Classifier: Programming Language :: Python :: 3.7
Classifier: Programming Language :: Python :: 3.8
Classifier: Programming Language :: Python :: 3.9
Classifier: Programming Language :: Python :: 3.10
Requires-Python: >=3.6
License-File: LICENSE
License-File: AUTHORS.rst
Requires-Dist: numpy (>=1.21)
